nl2action/__init__.py
nl2action/main.py
nl2action/prompts.py
nl2action-2025.12.21163026.dist-info/METADATA
nl2action-2025.12.21163026.dist-info/WHEEL
nl2action-2025.12.21163026.dist-info/top_level.txt
nl2action-2025.12.21163026.dist-info/RECORD
