Metadata-Version: 2.4
Name: nl2action
Version: 2025.12.21163026
Summary: A new package designed to interpret user-submitted text descriptions, such as notices or requests related to device control or automation, and convert them into structured commands or actions. By leve
Author-email: nl2action <hi@eugene.plus>
License: MIT
Project-URL: Homepage, https://github.com/chigwell/nl2action
Requires-Python: >=3.9
Requires-Dist: langchain-llm7>=0.0.0
Requires-Dist: llmatch-messages>=0.0.0
Requires-Dist: langchain-core>=0.3.0
